LICENSE
MANIFEST.in
README.md
requirements.txt
setup.py
compiler/__init__.py
compiler/api/__init__.py
compiler/api/compiler.py
compiler/api/source/auth_key.tl
compiler/api/source/main_api.tl
compiler/api/source/sys_msgs.tl
compiler/api/template/combinator.txt
compiler/api/template/type.txt
compiler/docs/__init__.py
compiler/docs/compiler.py
compiler/docs/template/page.txt
compiler/docs/template/toctree.txt
compiler/errors/__init__.py
compiler/errors/compiler.py
compiler/errors/sort.py
compiler/errors/source/303_SEE_OTHER.tsv
compiler/errors/source/400_BAD_REQUEST.tsv
compiler/errors/source/401_UNAUTHORIZED.tsv
compiler/errors/source/403_FORBIDDEN.tsv
compiler/errors/source/406_NOT_ACCEPTABLE.tsv
compiler/errors/source/420_FLOOD.tsv
compiler/errors/source/500_INTERNAL_SERVER_ERROR.tsv
compiler/errors/source/503_SERVICE_UNAVAILABLE.tsv
compiler/errors/template/class.txt
compiler/errors/template/sub_class.txt
pyrogramx/__init__.py
pyrogramx/client.py
pyrogramx/dispatcher.py
pyrogramx/emoji.py
pyrogramx/file_id.py
pyrogramx/filters.py
pyrogramx/mime_types.py
pyrogramx/py.typed
pyrogramx/sync.py
pyrogramx/utils.py
pyrogramx.egg-info/PKG-INFO
pyrogramx.egg-info/SOURCES.txt
pyrogramx.egg-info/dependency_links.txt
pyrogramx.egg-info/not-zip-safe
pyrogramx.egg-info/requires.txt
pyrogramx.egg-info/top_level.txt
pyrogramx/connection/__init__.py
pyrogramx/connection/connection.py
pyrogramx/connection/transport/__init__.py
pyrogramx/connection/transport/tcp/__init__.py
pyrogramx/connection/transport/tcp/tcp.py
pyrogramx/connection/transport/tcp/tcp_abridged.py
pyrogramx/connection/transport/tcp/tcp_abridged_o.py
pyrogramx/connection/transport/tcp/tcp_full.py
pyrogramx/connection/transport/tcp/tcp_intermediate.py
pyrogramx/connection/transport/tcp/tcp_intermediate_o.py
pyrogramx/crypto/__init__.py
pyrogramx/crypto/aes.py
pyrogramx/crypto/mtproto.py
pyrogramx/crypto/prime.py
pyrogramx/crypto/rsa.py
pyrogramx/enums/__init__.py
pyrogramx/enums/auto_name.py
pyrogramx/enums/chat_action.py
pyrogramx/enums/chat_event_action.py
pyrogramx/enums/chat_member_status.py
pyrogramx/enums/chat_members_filter.py
pyrogramx/enums/chat_type.py
pyrogramx/enums/message_entity_type.py
