Metadata-Version: 2.1
Name: pyrogramx
Version: 0.0.1
Summary: Elegant, modern and asynchronous Telegram MTProto API framework in Python for users and bots Forked From pyrogramx.org
Home-page: https://github.com/kalanakt
Download-URL: https://github.com/kalanakt/pyrogramx/releases/latest
Author: Kalana Kt
Author-email: kt@netronk.com
License: LGPLv3
Project-URL: Tracker, https://github.com/kalanakt/pyrogramx/issues
Project-URL: Community, https://t.me/pyrogramx
Project-URL: Source, https://github.com/kalanakt/pyrogramx
Project-URL: Documentation, https://docs.pyrogramx.org
Keywords: telegram chat messenger mtproto api client library python
Classifier: Development Status :: 5 - Production/Stable
Classifier: Intended Audience :: Developers
Classifier: Natural Language :: English
Classifier: License :: OSI Approved :: GNU Lesser General Public License v3 (LGPLv3)
Classifier: Operating System :: OS Independent
Classifier: Programming Language :: Python
Classifier: Programming Language :: Python :: 3
Classifier: Programming Language :: Python :: 3.7
Classifier: Programming Language :: Python :: 3.8
Classifier: Programming Language :: Python :: 3.9
Classifier: Programming Language :: Python :: 3.10
Classifier: Programming Language :: Python :: 3.11
Classifier: Programming Language :: Python :: Implementation
Classifier: Programming Language :: Python :: Implementation :: CPython
Classifier: Programming Language :: Python :: Implementation :: PyPy
Classifier: Topic :: Internet
Classifier: Topic :: Communications
Classifier: Topic :: Communications :: Chat
Classifier: Topic :: Software Development :: Libraries
Classifier: Topic :: Software Development :: Libraries :: Python Modules
Classifier: Topic :: Software Development :: Libraries :: Application Frameworks
Requires-Python: ~=3.7
License-File: LICENSE
Requires-Dist: pyaes==1.6.1
Requires-Dist: pysocks==1.7.1
